error_explorer_fastapi/__init__.py
error_explorer_fastapi/logging.py
error_explorer_fastapi/middleware.py
error_explorer_fastapi-1.2.0.dist-info/METADATA
error_explorer_fastapi-1.2.0.dist-info/WHEEL
error_explorer_fastapi-1.2.0.dist-info/RECORD
