Metadata-Version: 2.4
Name: error-explorer-fastapi
Version: 1.2.0
Summary: Error Explorer SDK for FastAPI
Project-URL: Documentation, https://docs.error-explorer.com/sdks/fastapi
Project-URL: Issues, https://github.com/error-explorer/error-explorer-fastapi/issues
Project-URL: Source, https://github.com/error-explorer/error-explorer-fastapi
Author-email: Error Explorer Team <support@error-explorer.com>
License-Expression: MIT
Keywords: error-explorer,error-tracking,fastapi,monitoring
Classifier: Development Status :: 5 - Production/Stable
Classifier: Framework :: FastAPI
Classifier: Intended Audience :: Developers
Classifier: License :: OSI Approved :: MIT License
Classifier: Programming Language :: Python :: 3
Classifier: Programming Language :: Python :: 3.9
Classifier: Programming Language :: Python :: 3.10
Classifier: Programming Language :: Python :: 3.11
Classifier: Programming Language :: Python :: 3.12
Classifier: Topic :: Software Development :: Libraries :: Python Modules
Requires-Python: >=3.9
Requires-Dist: error-explorer>=1.0.0
Requires-Dist: fastapi>=0.100.0
Requires-Dist: starlette>=0.27.0
Provides-Extra: dev
Requires-Dist: httpx>=0.24.0; extra == 'dev'
Requires-Dist: pytest-asyncio>=0.21.0; extra == 'dev'
Requires-Dist: pytest-cov>=4.0.0; extra == 'dev'
Requires-Dist: pytest>=7.0.0; extra == 'dev'
